exoming/__init__.py
exoming/command.py
exoming/exomIO.py
exoming-0.1.1.dist-info/METADATA
exoming-0.1.1.dist-info/WHEEL
exoming-0.1.1.dist-info/RECORD
