Metadata-Version: 2.1
Name: exoming
Version: 0.1.1
Summary: Exomiser launcher
License: cc4
Author: a.iazami
Requires-Python: >=3.11,<4.0
Classifier: License :: Other/Proprietary License
Classifier: Programming Language :: Python :: 3
Classifier: Programming Language :: Python :: 3.11
Requires-Dist: PyYAML (>=6.0,<7.0)
